toonio/__init__.py
toonio/response.py
toonio/status.py
toonio/core/__init__.py
toonio/core/basic_response.py
toonio/django/__init__.py
toonio/django/parser.py
toonio/django/render.py
toonio-0.1.2.dist-info/METADATA
toonio-0.1.2.dist-info/WHEEL
toonio-0.1.2.dist-info/top_level.txt
toonio-0.1.2.dist-info/RECORD
