Metadata-Version: 2.4
Name: toonio
Version: 0.1.2
Summary: toonio is a package for sending data in the Toon format
Author-email: Ehsan Amiri <ehsan.amiri.prog@email.com>
Project-URL: Homepage, https://github.com/ehs22n/toonio
Project-URL: Repository, https://github.com/ehs22n/toonio
Requires-Python: >=3.10
Requires-Dist: python-toon>=0.1.3
Requires-Dist: starlette>=0.50.0
Provides-Extra: django
Requires-Dist: Django>=5; extra == "django"
Requires-Dist: djangorestframework>=3.15; extra == "django"
Requires-Dist: python-toon>=0.1.3; extra == "django"
Provides-Extra: standard
Requires-Dist: python-toon>=0.1.3; extra == "standard"
